diving_station_py/__init__.py
diving_station_py/client.py
diving_station_py/constants.py
diving_station_py/event.py
diving_station_py/protocol/__init__.py
diving_station_py/protocol/connect.py
diving_station_py/protocol/constants.py
diving_station_py/protocol/controller.py
diving_station_py/protocol/device_info.py
diving_station_py/protocol/disconnect.py
diving_station_py/protocol/hand_bend.py
diving_station_py/protocol/hand_quat.py
diving_station_py/protocol/haptic.py
diving_station_py/protocol/wrist.py
diving_station_py-0.1.1.dist-info/METADATA
diving_station_py-0.1.1.dist-info/WHEEL
diving_station_py-0.1.1.dist-info/RECORD
