Metadata-Version: 2.3
Name: diving-station-py
Version: 0.1.1
Summary: A Python library for diving station
Author-email: OctSquid <pqvs6k96@s.okayama-u.ac.jp>
License: MIT
Requires-Python: >=3.9
Requires-Dist: asyncio>=3.4.3
Requires-Dist: python-osc>=1.9.3
